icemac.ab.locales-2.25-py3.7-nspkg.pth
icemac/ab/locales/__init__.py
icemac/ab/locales/configure.zcml
icemac/ab/locales/extract-no-zcml.zcml
icemac/ab/locales/extract.zcml
icemac/ab/locales/icemac.addressbook.pot
icemac/ab/locales/icemac.recurrence.pot
icemac/ab/locales/zope.mimetype.pot
icemac/ab/locales/de/LC_MESSAGES/icemac.addressbook.po
icemac/ab/locales/de/LC_MESSAGES/icemac.recurrence.po
icemac/ab/locales/de/LC_MESSAGES/zope.mimetype.po
icemac/ab/locales/en/LC_MESSAGES/icemac.addressbook.po
icemac/ab/locales/en/LC_MESSAGES/icemac.recurrence.po
icemac/ab/locales/en/LC_MESSAGES/zope.mimetype.po
icemac.ab.locales-2.25.dist-info/LICENSE.TXT
icemac.ab.locales-2.25.dist-info/METADATA
icemac.ab.locales-2.25.dist-info/WHEEL
icemac.ab.locales-2.25.dist-info/namespace_packages.txt
icemac.ab.locales-2.25.dist-info/top_level.txt
icemac.ab.locales-2.25.dist-info/RECORD
