Metadata-Version: 2.1
Name: icemac.ab.locales
Version: 2.25
Summary: Translations for icemac.addressbook and icemac.ab.* packages.
Home-page: https://pypi.org/project/icemac.ab.locales
Author: Michael Howitz
Author-email: icemac@gmx.net
License: MIT
Keywords: icemac addressbook address book locales translation i18n
Platform: UNKNOWN
Classifier: Development Status :: 5 - Production/Stable
Classifier: Environment :: Web Environment
Classifier: Framework :: Zope3
Classifier: Intended Audience :: Developers
Classifier: License :: OSI Approved :: MIT License
Classifier: Natural Language :: English
Classifier: Natural Language :: German
Classifier: Operating System :: OS Independent
Classifier: Programming Language :: Python :: 2
Classifier: Programming Language :: Python :: 2 :: Only
Classifier: Programming Language :: Python :: 2.7
Classifier: Programming Language :: Python :: Implementation :: CPython
Classifier: Topic :: Internet :: WWW/HTTP
Requires-Dist: setuptools
Requires-Dist: zope.i18n
Provides-Extra: compile
Requires-Dist: python-gettext ; extra == 'compile'
Provides-Extra: extract
Requires-Dist: icemac.ab.calendar ; extra == 'extract'
Requires-Dist: icemac.ab.importer ; extra == 'extract'
Requires-Dist: icemac.ab.importxls ; extra == 'extract'
Requires-Dist: icemac.addressbook (>=9.0.dev0) ; extra == 'extract'
Provides-Extra: extractzopemimetype
Requires-Dist: zope.mimetype ; extra == 'extractzopemimetype'
